{
  "name": "mockup-hero",
  "categories": [
    "hero",
    "mainsection"
  ],
  "description": "A modern hero section with a phone mockup image which when hovered has a 3D like animation and a sleek design. Used for SaaS products, hero sections, etc.",
  "type": "registry:block",
  "dependencies": [
    "framer-motion",
    "lucide-react",
    "next-themes",
    "react"
  ],
  "registryDependencies": [
    "https://blocks.mvp-subha.me/r/utils.json",
    "https://blocks.mvp-subha.me/r/button.json",
    "https://blocks.mvp-subha.me/r/phone-mockup.json"
  ],
  "files": [
    {
      "type": "registry:block",
      "content": "'use client';\r\n\r\nimport React, { useRef, useEffect, useState } from 'react';\r\nimport {\r\n  motion,\r\n  useAnimation,\r\n  useInView,\r\n  useScroll,\r\n  useTransform,\r\n  useMotionValue,\r\n} from 'framer-motion';\r\nimport { cn } from '@/lib/utils';\r\nimport { Button } from '@/components/ui/button';\r\nimport PhoneMockup from '@/components/ui/phone-mockup';\r\nimport { useTheme } from 'next-themes';\r\nimport { ArrowRight, Sparkles } from 'lucide-react';\r\n\r\nexport default function LucyHero() {\r\n  const { theme } = useTheme();\r\n  const isDark = theme === 'dark';\r\n  const heroRef = useRef<HTMLDivElement>(null);\r\n  const mockupRef = useRef<HTMLDivElement>(null);\r\n  const isInView = useInView(heroRef, { once: false, amount: 0.3 });\r\n  const controls = useAnimation();\r\n  const { scrollYProgress } = useScroll({\r\n    target: heroRef,\r\n    offset: ['start start', 'end start'],\r\n  });\r\n\r\n  const backgroundY = useTransform(scrollYProgress, [0, 1], [0, 100]);\r\n  const contentY = useTransform(scrollYProgress, [0, 1], [0, 50]);\r\n\r\n  const [isHovered, setIsHovered] = useState(false);\r\n  const mouseX = useMotionValue(0);\r\n  const mouseY = useMotionValue(0);\r\n\r\n  const rotateX = useTransform(mouseY, [-0.5, 0, 0.5], [20, 0, -20]);\r\n  const rotateY = useTransform(mouseX, [-0.5, 0, 0.5], [-20, 0, 20]);\r\n\r\n  useEffect(() => {\r\n    if (isInView) {\r\n      controls.start('visible');\r\n    }\r\n  }, [isInView, controls]);\r\n\r\n  const GradientText = ({\r\n    children,\r\n    className,\r\n  }: {\r\n    children: React.ReactNode;\r\n    className?: string;\r\n  }) => (\r\n    <span\r\n      className={cn(\r\n        'from-primary dark:from-primary bg-gradient-to-r via-rose-400 to-rose-300 bg-clip-text text-transparent dark:via-rose-300 dark:to-red-400',\r\n        className,\r\n      )}\r\n    >\r\n      {children}\r\n    </span>\r\n  );\r\n\r\n  return (\r\n    <div\r\n      ref={heroRef}\r\n      className=\"bg-background relative min-h-screen w-full overflow-hidden py-16\"\r\n    >\r\n      <motion.div className=\"absolute inset-0 z-0\" style={{ y: backgroundY }}>\r\n        <div className=\"absolute inset-0 bg-[radial-gradient(ellipse_80%_80%_at_50%_-20%,rgba(229,62,62,0.2),rgba(255,255,255,0))] dark:bg-[radial-gradient(ellipse_80%_80%_at_50%_-20%,rgba(229,62,62,0.15),rgba(30,30,40,0))]\"></div>\r\n\r\n        <div className=\"absolute inset-0 bg-[radial-gradient(circle_at_10%_90%,rgba(229,62,62,0.08),transparent_50%)] dark:bg-[radial-gradient(circle_at_10%_90%,rgba(120,119,198,0.1),transparent_50%)]\"></div>\r\n        <div className=\"absolute inset-0 bg-[radial-gradient(circle_at_90%_20%,rgba(255,100,150,0.05),transparent_50%)] dark:bg-[radial-gradient(circle_at_90%_20%,rgba(100,150,255,0.05),transparent_50%)]\"></div>\r\n\r\n        <div className=\"bg-noise absolute inset-0 opacity-[0.02]\"></div>\r\n        <div className=\"absolute inset-0 opacity-5 backdrop-blur-[100px]\"></div>\r\n        <div className=\"absolute inset-0 [background-image:linear-gradient(rgba(229,62,62,0.05)_1px,transparent_1px),linear-gradient(to_right,rgba(229,62,62,0.05)_1px,transparent_1px)] [background-size:40px_40px] opacity-[0.03] dark:[background-image:linear-gradient(rgba(200,200,255,0.05)_1px,transparent_1px),linear-gradient(to_right,rgba(200,200,255,0.05)_1px,transparent_1px)] dark:opacity-[0.02]\"></div>\r\n      </motion.div>\r\n\r\n      <motion.div\r\n        className=\"relative z-10 container mx-auto max-w-7xl\"\r\n        style={{ y: contentY }}\r\n      >\r\n        <div className=\"grid items-center gap-16 md:grid-cols-2\">\r\n          <motion.div\r\n            variants={{\r\n              hidden: { opacity: 0, x: -50 },\r\n              visible: {\r\n                opacity: 1,\r\n                x: 0,\r\n                transition: {\r\n                  duration: 0.7,\r\n                  staggerChildren: 0.2,\r\n                },\r\n              },\r\n            }}\r\n            initial=\"hidden\"\r\n            animate={controls}\r\n            className=\"flex flex-col text-center md:text-left\"\r\n          >\r\n            <motion.div\r\n              variants={{\r\n                hidden: { opacity: 0, y: 20 },\r\n                visible: { opacity: 1, y: 0 },\r\n              }}\r\n            >\r\n              <h2 className=\"text-foreground mb-6 text-4xl leading-tight font-bold tracking-tight md:text-5xl lg:text-6xl\">\r\n                LU-cy bridges <GradientText>Web3</GradientText> and{' '}\r\n                <GradientText>AI</GradientText> platforms for dev teams\r\n              </h2>\r\n            </motion.div>\r\n\r\n            <motion.p\r\n              variants={{\r\n                hidden: { opacity: 0, y: 20 },\r\n                visible: { opacity: 1, y: 0 },\r\n              }}\r\n              className=\"text-muted-foreground mb-8 text-lg leading-relaxed\"\r\n            >\r\n              The future is a blend of intelligence and decentralization. LU-cy\r\n              connects AI tools with Web3 infrastructure, giving developers the\r\n              power to build beyond limits. One platform.{' '}\r\n              <span className=\"text-foreground font-semibold\">\r\n                Endless potential.\r\n              </span>\r\n            </motion.p>\r\n\r\n            <motion.div\r\n              variants={{\r\n                hidden: { opacity: 0, y: 20 },\r\n                visible: { opacity: 1, y: 0 },\r\n              }}\r\n              className=\"flex flex-wrap justify-center gap-4 md:justify-start\"\r\n            >\r\n              <motion.div\r\n                whileHover={{ scale: 1.05 }}\r\n                whileTap={{ scale: 0.95 }}\r\n                className=\"relative\"\r\n              >\r\n                <Button className=\"relative rounded-full\">\r\n                  Explore\r\n                  <Sparkles className=\"h-4 w-4\" />\r\n                </Button>\r\n              </motion.div>\r\n\r\n              <motion.div\r\n                whileHover={{ scale: 1.05 }}\r\n                whileTap={{ scale: 0.95 }}\r\n                className=\"relative\"\r\n              >\r\n                <div className=\"bg-background/50 absolute inset-0 -z-10 rounded-full backdrop-blur-sm\"></div>\r\n                <Button\r\n                  variant=\"outline\"\r\n                  className=\"border-primary/20 hover:border-primary/30 hover:bg-primary/5 rounded-full backdrop-blur-sm transition-all duration-300\"\r\n                >\r\n                  Learn More <ArrowRight className=\"ml-2 h-4 w-4\" />\r\n                </Button>\r\n              </motion.div>\r\n            </motion.div>\r\n\r\n            <motion.div\r\n              variants={{ hidden: { opacity: 0 }, visible: { opacity: 1 } }}\r\n              className=\"mt-10 flex flex-wrap justify-center gap-3 md:justify-start\"\r\n            >\r\n              {['Web3 Ready', 'AI Powered', 'Developer First'].map(\r\n                (feature, index) => (\r\n                  <motion.div\r\n                    key={feature}\r\n                    initial={{ opacity: 0, y: 20 }}\r\n                    animate={{ opacity: 1, y: 0 }}\r\n                    transition={{ delay: 0.6 + index * 0.1 }}\r\n                    whileHover={{ scale: 1.05, y: -2 }}\r\n                    className=\"text-foreground relative rounded-full px-4 py-1.5 text-sm font-medium shadow-sm\"\r\n                  >\r\n                    <div className=\"border-primary/10 bg-background/80 dark:bg-background/30 absolute inset-0 rounded-full border backdrop-blur-md dark:border-white/5\"></div>\r\n                    <div className=\"via-primary/20 dark:via-primary/30 absolute bottom-0 left-1/2 h-px w-1/2 -translate-x-1/2 bg-gradient-to-r from-rose-500/0 to-rose-500/0 dark:from-blue-500/0 dark:to-indigo-500/0\"></div>\r\n\r\n                    <span className=\"relative z-10\">{feature}</span>\r\n                  </motion.div>\r\n                ),\r\n              )}\r\n            </motion.div>\r\n          </motion.div>\r\n\r\n          <motion.div\r\n            variants={{\r\n              hidden: { opacity: 0, scale: 0.9 },\r\n              visible: {\r\n                opacity: 1,\r\n                scale: 1,\r\n                transition: {\r\n                  duration: 0.8,\r\n                  type: 'spring',\r\n                  stiffness: 100,\r\n                },\r\n              },\r\n            }}\r\n            initial=\"hidden\"\r\n            animate={controls}\r\n            ref={mockupRef}\r\n            className=\"relative mx-auto flex justify-center perspective-distant transform-3d\"\r\n            onMouseMove={(e) => {\r\n              const rect = e.currentTarget.getBoundingClientRect();\r\n              const x = (e.clientX - rect.left) / rect.width - 0.5;\r\n              const y = (e.clientY - rect.top) / rect.height - 0.5;\r\n              mouseX.set(x);\r\n              mouseY.set(y);\r\n\r\n              if (!isHovered) {\r\n                setIsHovered(true);\r\n              }\r\n            }}\r\n            onMouseLeave={() => {\r\n              mouseX.set(0);\r\n              mouseY.set(0);\r\n              setIsHovered(false);\r\n            }}\r\n          >\r\n            <motion.div\r\n              className=\"relative z-10 transform-3d\"\r\n              style={{\r\n                rotateX: rotateX,\r\n                rotateY: rotateY,\r\n                scale: isHovered ? 1.05 : 1,\r\n              }}\r\n              transition={{\r\n                scale: {\r\n                  duration: 0.3,\r\n                  type: 'spring',\r\n                  ease: [0.34, 1.56, 0.64, 1],\r\n                },\r\n              }}\r\n            >\r\n              <PhoneMockup\r\n                imageUrl={\r\n                  isDark\r\n                    ? 'https://i.postimg.cc/D0cjZsVd/mobile-dark.webp'\r\n                    : 'https://i.postimg.cc/L6NQFz3m/mobile-light.webp'\r\n                }\r\n                alt=\"LU-cy mobile app\"\r\n                glowColor={\r\n                  isDark ? 'rgba(229, 62, 62, 0.5)' : 'rgba(229, 62, 62, 0.25)'\r\n                }\r\n                className=\"max-w-[380px]\"\r\n              />\r\n            </motion.div>\r\n          </motion.div>\r\n        </div>\r\n      </motion.div>\r\n    </div>\r\n  );\r\n}\r\n",
      "path": "/components/petalui/mainsections/hero/mockup-hero.tsx",
      "target": "components/petalui/mockup-hero.tsx"
    }
  ]
}