{
  "name": "slider",
  "description": "A slider component for selecting a value from a range. Official Shadcn UI component.",
  "categories": [
    "slider",
    "form-element",
    "shadcn"
  ],
  "type": "registry:ui",
  "dependencies": [
    "@radix-ui/react-slider"
  ],
  "files": [
    {
      "type": "registry:ui",
      "content": "'use client';\r\n\r\nimport * as React from 'react';\r\nimport * as SliderPrimitive from '@radix-ui/react-slider';\r\n\r\nimport { cn } from '@/lib/utils';\r\n\r\nconst Slider = React.forwardRef<\r\n  React.ElementRef<typeof SliderPrimitive.Root>,\r\n  React.ComponentPropsWithoutRef<typeof SliderPrimitive.Root>\r\n>(({ className, ...props }, ref) => (\r\n  <SliderPrimitive.Root\r\n    ref={ref}\r\n    className={cn(\r\n      'relative flex w-full touch-none items-center select-none',\r\n      className,\r\n    )}\r\n    {...props}\r\n  >\r\n    <SliderPrimitive.Track className=\"bg-secondary relative h-2 w-full grow overflow-hidden rounded-full\">\r\n      <SliderPrimitive.Range className=\"bg-primary absolute h-full\" />\r\n    </SliderPrimitive.Track>\r\n    <SliderPrimitive.Thumb className=\"border-primary bg-background ring-offset-background focus-visible:ring-ring block h-5 w-5 rounded-full border-2 transition-colors focus-visible:ring-2 focus-visible:ring-offset-2 focus-visible:outline-none disabled:pointer-events-none disabled:opacity-50\" />\r\n  </SliderPrimitive.Root>\r\n));\r\nSlider.displayName = SliderPrimitive.Root.displayName;\r\n\r\nexport { Slider };\r\n",
      "path": "/components/ui/slider.tsx",
      "target": "components/ui/slider.tsx"
    }
  ]
}